mapbufferaccel.cp38-win_amd64.pyd
mapbuffer/__init__.py
mapbuffer/compression.py
mapbuffer/exceptions.py
mapbuffer/intmap.py
mapbuffer/lib.py
mapbuffer/mapbuffer.py
mapbuffer-1.1.0.dist-info/AUTHORS
mapbuffer-1.1.0.dist-info/LICENSE
mapbuffer-1.1.0.dist-info/METADATA
mapbuffer-1.1.0.dist-info/WHEEL
mapbuffer-1.1.0.dist-info/pbr.json
mapbuffer-1.1.0.dist-info/top_level.txt
mapbuffer-1.1.0.dist-info/RECORD
