Metadata-Version: 2.2
Name: mapbuffer
Version: 1.1.0
Summary: Serializable map of integers to bytes with near zero parsing.
Home-page: https://github.com/seung-lab/mapbuffer/
Author: William Silversmith
Author-email: ws9@princeton.edu
License: BSD-3-Clause
Classifier: Intended Audience :: Developers
Classifier: Development Status :: 5 - Production/Stable
Classifier: Programming Language :: Python :: 3
Classifier: Programming Language :: Python :: 3.9
Classifier: Programming Language :: Python :: 3.10
Classifier: Programming Language :: Python :: 3.11
Classifier: Programming Language :: Python :: 3.12
Classifier: Programming Language :: Python :: 3.13
Classifier: Programming Language :: Python :: 3.14
Classifier: Topic :: Software Development :: Libraries :: Python Modules
Requires-Python: >=3.8,<4.0
License-File: LICENSE
License-File: AUTHORS
Requires-Dist: brotli
Requires-Dist: crc32c
Requires-Dist: deflate>=0.2.0
Requires-Dist: numpy
Requires-Dist: tqdm
Requires-Dist: zstandard
Dynamic: author
Dynamic: author-email
Dynamic: classifier
Dynamic: description
Dynamic: description-content-type
Dynamic: home-page
Dynamic: license
Dynamic: requires-dist
Dynamic: requires-python
Dynamic: summary
